{
	"name": "vNames 🗃️",
	"events": [
		{
			"eventType": "comment",
			"text": "Animations"
		},
		{
			"eventType": "variable",
			"name": "ANIM_Walking",
			"type": "string",
			"initialValue": "Walking",
			"comment": "",
			"isStatic": false,
			"isConstant": true,
			"sid": 926677348791607
		},
		{
			"eventType": "variable",
			"name": "ANIM_Idle",
			"type": "string",
			"initialValue": "Idle",
			"comment": "",
			"isStatic": false,
			"isConstant": true,
			"sid": 503392850679348
		},
		{
			"eventType": "comment",
			"text": "Audio"
		},
		{
			"eventType": "variable",
			"name": "AUDIO_BGM",
			"type": "string",
			"initialValue": "BGM",
			"comment": "",
			"isStatic": false,
			"isConstant": true,
			"sid": 472471421489667
		},
		{
			"eventType": "variable",
			"name": "AUDIO_SFX",
			"type": "string",
			"initialValue": "SFX",
			"comment": "",
			"isStatic": false,
			"isConstant": true,
			"sid": 980820014768865
		},
		{
			"eventType": "comment",
			"text": "Frames"
		},
		{
			"eventType": "variable",
			"name": "FRAME_Standing",
			"type": "string",
			"initialValue": "Standing",
			"comment": "",
			"isStatic": false,
			"isConstant": true,
			"sid": 411425537465178
		},
		{
			"eventType": "comment",
			"text": "Image points"
		},
		{
			"eventType": "variable",
			"name": "IP_Enemy_DamageNumber",
			"type": "string",
			"initialValue": "DamageNumber",
			"comment": "",
			"isStatic": false,
			"isConstant": true,
			"sid": 656461353568013
		},
		{
			"eventType": "comment",
			"text": "Layers"
		},
		{
			"eventType": "variable",
			"name": "LAYER_UI",
			"type": "string",
			"initialValue": "UI",
			"comment": "",
			"isStatic": false,
			"isConstant": true,
			"sid": 708340787910216
		},
		{
			"eventType": "variable",
			"name": "LAYER_Main",
			"type": "string",
			"initialValue": "Main",
			"comment": "",
			"isStatic": false,
			"isConstant": true,
			"sid": 724271032649710
		},
		{
			"eventType": "comment",
			"text": "JSON keys"
		},
		{
			"eventType": "variable",
			"name": "KEY_Add",
			"type": "string",
			"initialValue": "Add",
			"comment": "",
			"isStatic": false,
			"isConstant": true,
			"sid": 709355757484171
		},
		{
			"eventType": "variable",
			"name": "KEY_Amount",
			"type": "string",
			"initialValue": "Amount",
			"comment": "",
			"isStatic": false,
			"isConstant": true,
			"sid": 302328234135474
		},
		{
			"eventType": "variable",
			"name": "KEY_AngleOffset",
			"type": "string",
			"initialValue": "AngleOffset",
			"comment": "",
			"isStatic": false,
			"isConstant": true,
			"sid": 106917551357912
		},
		{
			"eventType": "variable",
			"name": "KEY_BlockMovement",
			"type": "string",
			"initialValue": "BlockMovement",
			"comment": "",
			"isStatic": false,
			"isConstant": true,
			"sid": 944984716583836
		},
		{
			"eventType": "variable",
			"name": "KEY_Bonus_Enemy_Spawn_Cooldown_Multiplier",
			"type": "string",
			"initialValue": "Bonus_Enemy_Spawn_Cooldown_Multiplier",
			"comment": "",
			"isStatic": false,
			"isConstant": true,
			"sid": 877156241595011
		},
		{
			"eventType": "variable",
			"name": "KEY_Bonus_Experience_Multiplier",
			"type": "string",
			"initialValue": "Bonus_Experience_Multiplier",
			"comment": "",
			"isStatic": false,
			"isConstant": true,
			"sid": 446231297191168
		},
		{
			"eventType": "variable",
			"name": "KEY_Bonus_Healing_Multiplier",
			"type": "string",
			"initialValue": "Bonus_Healing_Multiplier",
			"comment": "",
			"isStatic": false,
			"isConstant": true,
			"sid": 945364366268268
		},
		{
			"eventType": "variable",
			"name": "KEY_Bonus_Weapon_Amount_Extra",
			"type": "string",
			"initialValue": "Bonus_Weapon_Amount_Extra",
			"comment": "",
			"isStatic": false,
			"isConstant": true,
			"sid": 221695903888076
		},
		{
			"eventType": "variable",
			"name": "KEY_Bonus_Weapon_Cooldown_Multiplier",
			"type": "string",
			"initialValue": "Bonus_Weapon_Cooldown_Multiplier",
			"comment": "",
			"isStatic": false,
			"isConstant": true,
			"sid": 739398101416171
		},
		{
			"eventType": "variable",
			"name": "KEY_Bonus_Weapon_Damage_Multiplier",
			"type": "string",
			"initialValue": "Bonus_Weapon_Damage_Multiplier",
			"comment": "",
			"isStatic": false,
			"isConstant": true,
			"sid": 891754243403284
		},
		{
			"eventType": "variable",
			"name": "KEY_Bonus_Weapon_Size_Multiplier",
			"type": "string",
			"initialValue": "Bonus_Weapon_Size_Multiplier",
			"comment": "",
			"isStatic": false,
			"isConstant": true,
			"sid": 407179137716937
		},
		{
			"eventType": "variable",
			"name": "KEY_Cooldown",
			"type": "string",
			"initialValue": "Cooldown",
			"comment": "",
			"isStatic": false,
			"isConstant": true,
			"sid": 757964511800341
		},
		{
			"eventType": "variable",
			"name": "KEY_Damage",
			"type": "string",
			"initialValue": "Damage",
			"comment": "",
			"isStatic": false,
			"isConstant": true,
			"sid": 728829847967031
		},
		{
			"eventType": "variable",
			"name": "KEY_Description",
			"type": "string",
			"initialValue": "Description",
			"comment": "",
			"isStatic": false,
			"isConstant": true,
			"sid": 255335715483182
		},
		{
			"eventType": "variable",
			"name": "KEY_Distance",
			"type": "string",
			"initialValue": "Distance",
			"comment": "",
			"isStatic": false,
			"isConstant": true,
			"sid": 823037978565221
		},
		{
			"eventType": "variable",
			"name": "KEY_DropValueToLevelDivider",
			"type": "string",
			"initialValue": "DropValueToLevelDivider",
			"comment": "",
			"isStatic": false,
			"isConstant": true,
			"sid": 523644740878634
		},
		{
			"eventType": "variable",
			"name": "KEY_Enemies",
			"type": "string",
			"initialValue": "Enemies",
			"comment": "",
			"isStatic": false,
			"isConstant": true,
			"sid": 260309811983460
		},
		{
			"eventType": "variable",
			"name": "KEY_EnemySpawn",
			"type": "string",
			"initialValue": "EnemySpawn",
			"comment": "",
			"isStatic": false,
			"isConstant": true,
			"sid": 194085676929715
		},
		{
			"eventType": "variable",
			"name": "KEY_EnemySpawnAmountPerWave",
			"type": "string",
			"initialValue": "EnemySpawnAmountPerWave",
			"comment": "",
			"isStatic": false,
			"isConstant": true,
			"sid": 155215406098268
		},
		{
			"eventType": "variable",
			"name": "KEY_EnemySpawnCooldown",
			"type": "string",
			"initialValue": "EnemySpawnCooldown",
			"comment": "",
			"isStatic": false,
			"isConstant": true,
			"sid": 741062812388619
		},
		{
			"eventType": "variable",
			"name": "KEY_EnemySpawnCycles",
			"type": "string",
			"initialValue": "EnemySpawnCycles",
			"comment": "",
			"isStatic": false,
			"isConstant": true,
			"sid": 199564196662953
		},
		{
			"eventType": "variable",
			"name": "KEY_EnemySpawnFixed",
			"type": "string",
			"initialValue": "EnemySpawnFixed",
			"comment": "",
			"isStatic": false,
			"isConstant": true,
			"sid": 703608357685707
		},
		{
			"eventType": "variable",
			"name": "KEY_EnemySpawnPool",
			"type": "string",
			"initialValue": "EnemySpawnPool",
			"comment": "",
			"isStatic": false,
			"isConstant": true,
			"sid": 462972560956048
		},
		{
			"eventType": "variable",
			"name": "KEY_EnemyTeleport",
			"type": "string",
			"initialValue": "EnemyTeleport",
			"comment": "",
			"isStatic": false,
			"isConstant": true,
			"sid": 389803386072843
		},
		{
			"eventType": "variable",
			"name": "KEY_Experience",
			"type": "string",
			"initialValue": "Experience",
			"comment": "",
			"isStatic": false,
			"isConstant": true,
			"sid": 813389467900788
		},
		{
			"eventType": "variable",
			"name": "KEY_Experience_Target",
			"type": "string",
			"initialValue": "Experience_Target",
			"comment": "",
			"isStatic": false,
			"isConstant": true,
			"sid": 267184944738624
		},
		{
			"eventType": "variable",
			"name": "KEY_Experience_Target_Multiplier",
			"type": "string",
			"initialValue": "Experience_Target_Multiplier",
			"comment": "",
			"isStatic": false,
			"isConstant": true,
			"sid": 661251184749942
		},
		{
			"eventType": "variable",
			"name": "KEY_Healing",
			"type": "string",
			"initialValue": "Healing",
			"comment": "",
			"isStatic": false,
			"isConstant": true,
			"sid": 235009014076591
		},
		{
			"eventType": "variable",
			"name": "KEY_Health",
			"type": "string",
			"initialValue": "Health",
			"comment": "",
			"isStatic": false,
			"isConstant": true,
			"sid": 193700461985965
		},
		{
			"eventType": "variable",
			"name": "KEY_Health_Max",
			"type": "string",
			"initialValue": "Health_Max",
			"comment": "",
			"isStatic": false,
			"isConstant": true,
			"sid": 102741378861192
		},
		{
			"eventType": "variable",
			"name": "KEY_Health_Multiplier",
			"type": "string",
			"initialValue": "Health_Max_Multiplier",
			"comment": "",
			"isStatic": false,
			"isConstant": true,
			"sid": 876298997252055
		},
		{
			"eventType": "variable",
			"name": "KEY_Height",
			"type": "string",
			"initialValue": "Height",
			"comment": "",
			"isStatic": false,
			"isConstant": true,
			"sid": 487066448985697
		},
		{
			"eventType": "variable",
			"name": "KEY_Icon",
			"type": "string",
			"initialValue": "Icon",
			"comment": "",
			"isStatic": false,
			"isConstant": true,
			"sid": 300756568646211
		},
		{
			"eventType": "variable",
			"name": "KEY_Items",
			"type": "string",
			"initialValue": "Items",
			"comment": "",
			"isStatic": false,
			"isConstant": true,
			"sid": 990155293678732
		},
		{
			"eventType": "variable",
			"name": "KEY_ItemSpawnMinimum",
			"type": "string",
			"initialValue": "ItemSpawnMinimum",
			"comment": "",
			"isStatic": false,
			"isConstant": true,
			"sid": 735320469579723
		},
		{
			"eventType": "variable",
			"name": "KEY_ItemSpawnPool",
			"type": "string",
			"initialValue": "ItemSpawnPool",
			"comment": "",
			"isStatic": false,
			"isConstant": true,
			"sid": 675425500838668
		},
		{
			"eventType": "variable",
			"name": "KEY_Label",
			"type": "string",
			"initialValue": "Label",
			"comment": "",
			"isStatic": false,
			"isConstant": true,
			"sid": 665338597903307
		},
		{
			"eventType": "variable",
			"name": "KEY_Level",
			"type": "string",
			"initialValue": "Level",
			"comment": "",
			"isStatic": false,
			"isConstant": true,
			"sid": 694929315152815
		},
		{
			"eventType": "variable",
			"name": "KEY_Map",
			"type": "string",
			"initialValue": "Map",
			"comment": "",
			"isStatic": false,
			"isConstant": true,
			"sid": 923828765477710
		},
		{
			"eventType": "variable",
			"name": "KEY_MovementSpeed",
			"type": "string",
			"initialValue": "MovementSpeed",
			"comment": "",
			"isStatic": false,
			"isConstant": true,
			"sid": 514107089827304
		},
		{
			"eventType": "variable",
			"name": "KEY_MovementAcceleration",
			"type": "string",
			"initialValue": "MovementAcceleration",
			"comment": "",
			"isStatic": false,
			"isConstant": true,
			"sid": 830534511767597
		},
		{
			"eventType": "variable",
			"name": "KEY_MovementDeceleration",
			"type": "string",
			"initialValue": "MovementDeceleration",
			"comment": "",
			"isStatic": false,
			"isConstant": true,
			"sid": 982570091533426
		},
		{
			"eventType": "variable",
			"name": "KEY_Multiply",
			"type": "string",
			"initialValue": "Multiply",
			"comment": "",
			"isStatic": false,
			"isConstant": true,
			"sid": 612566766668746
		},
		{
			"eventType": "variable",
			"name": "KEY_Name",
			"type": "string",
			"initialValue": "Name",
			"comment": "",
			"isStatic": false,
			"isConstant": true,
			"sid": 213186804235384
		},
		{
			"eventType": "variable",
			"name": "KEY_OrbitRadius",
			"type": "string",
			"initialValue": "OrbitRadius",
			"comment": "",
			"isStatic": false,
			"isConstant": true,
			"sid": 255225496856299
		},
		{
			"eventType": "variable",
			"name": "KEY_OrbitSpeed",
			"type": "string",
			"initialValue": "OrbitSpeed",
			"comment": "",
			"isStatic": false,
			"isConstant": true,
			"sid": 321267012438618
		},
		{
			"eventType": "variable",
			"name": "KEY_PickupDistance",
			"type": "string",
			"initialValue": "PickupDistance",
			"comment": "",
			"isStatic": false,
			"isConstant": true,
			"sid": 983768474373603
		},
		{
			"eventType": "variable",
			"name": "KEY_PierceLimit",
			"type": "string",
			"initialValue": "PierceLimit",
			"comment": "",
			"isStatic": false,
			"isConstant": true,
			"sid": 909545994641247
		},
		{
			"eventType": "variable",
			"name": "KEY_Pin",
			"type": "string",
			"initialValue": "Pin",
			"comment": "",
			"isStatic": false,
			"isConstant": true,
			"sid": 232825710843520
		},
		{
			"eventType": "variable",
			"name": "KEY_Player",
			"type": "string",
			"initialValue": "Player",
			"comment": "",
			"isStatic": false,
			"isConstant": true,
			"sid": 725029190180261
		},
		{
			"eventType": "variable",
			"name": "KEY_Pools",
			"type": "string",
			"initialValue": "Pools",
			"comment": "",
			"isStatic": false,
			"isConstant": true,
			"sid": 974911269037936
		},
		{
			"eventType": "variable",
			"name": "KEY_PositionRandom1",
			"type": "string",
			"initialValue": "PositionRandom1",
			"comment": "",
			"isStatic": false,
			"isConstant": true,
			"sid": 695980413314861
		},
		{
			"eventType": "variable",
			"name": "KEY_PositionRandom2",
			"type": "string",
			"initialValue": "PositionRandom2",
			"comment": "",
			"isStatic": false,
			"isConstant": true,
			"sid": 846814970302667
		},
		{
			"eventType": "variable",
			"name": "KEY_Rule_Max",
			"type": "string",
			"initialValue": "Rule_Max",
			"comment": "",
			"isStatic": false,
			"isConstant": true,
			"sid": 245743096954132
		},
		{
			"eventType": "variable",
			"name": "KEY_Rule_Value",
			"type": "string",
			"initialValue": "Rule_Value",
			"comment": "",
			"isStatic": false,
			"isConstant": true,
			"sid": 336932584532681
		},
		{
			"eventType": "variable",
			"name": "KEY_Scale",
			"type": "string",
			"initialValue": "Scale",
			"comment": "",
			"isStatic": false,
			"isConstant": true,
			"sid": 242774993217273
		},
		{
			"eventType": "variable",
			"name": "KEY_StaticAngle",
			"type": "string",
			"initialValue": "StaticAngle",
			"comment": "",
			"isStatic": false,
			"isConstant": true,
			"sid": 196735625579872
		},
		{
			"eventType": "variable",
			"name": "KEY_Timeout",
			"type": "string",
			"initialValue": "Timeout",
			"comment": "",
			"isStatic": false,
			"isConstant": true,
			"sid": 275286016797896
		},
		{
			"eventType": "variable",
			"name": "KEY_Upgrades",
			"type": "string",
			"initialValue": "Upgrades",
			"comment": "",
			"isStatic": false,
			"isConstant": true,
			"sid": 129044761791842
		},
		{
			"eventType": "variable",
			"name": "KEY_WallThickness",
			"type": "string",
			"initialValue": "WallThickness",
			"comment": "",
			"isStatic": false,
			"isConstant": true,
			"sid": 745102957355950
		},
		{
			"eventType": "variable",
			"name": "KEY_WaveLoopTo",
			"type": "string",
			"initialValue": "WaveLoopTo",
			"comment": "",
			"isStatic": false,
			"isConstant": true,
			"sid": 450719927094897
		},
		{
			"eventType": "variable",
			"name": "KEY_Waves",
			"type": "string",
			"initialValue": "Waves",
			"comment": "",
			"isStatic": false,
			"isConstant": true,
			"sid": 641746479686938
		},
		{
			"eventType": "variable",
			"name": "KEY_WeaponRequirement",
			"type": "string",
			"initialValue": "WeaponRequirement",
			"comment": "",
			"isStatic": false,
			"isConstant": true,
			"sid": 855705167315955
		},
		{
			"eventType": "variable",
			"name": "KEY_Weapons",
			"type": "string",
			"initialValue": "Weapons",
			"comment": "",
			"isStatic": false,
			"isConstant": true,
			"sid": 488366486156130
		},
		{
			"eventType": "variable",
			"name": "KEY_Width",
			"type": "string",
			"initialValue": "Width",
			"comment": "",
			"isStatic": false,
			"isConstant": true,
			"sid": 150953982884702
		},
		{
			"eventType": "comment",
			"text": "Loops"
		},
		{
			"eventType": "variable",
			"name": "LOOP_Cell_X",
			"type": "string",
			"initialValue": "Cell_X",
			"comment": "",
			"isStatic": false,
			"isConstant": true,
			"sid": 199283899884040
		},
		{
			"eventType": "variable",
			"name": "LOOP_Cell_Y",
			"type": "string",
			"initialValue": "Cell_Y",
			"comment": "",
			"isStatic": false,
			"isConstant": true,
			"sid": 488267742521129
		},
		{
			"eventType": "variable",
			"name": "LOOP_Decorations_Per_Cell",
			"type": "string",
			"initialValue": "Decorations_Per_Cell",
			"comment": "",
			"isStatic": false,
			"isConstant": true,
			"sid": 444973302307180
		},
		{
			"eventType": "variable",
			"name": "LOOP_Obstacles_Per_Cell",
			"type": "string",
			"initialValue": "Obstacles_Per_Cell",
			"comment": "",
			"isStatic": false,
			"isConstant": true,
			"sid": 797025420437282
		},
		{
			"eventType": "comment",
			"text": "Probability tables"
		},
		{
			"eventType": "variable",
			"name": "PT_Enemies",
			"type": "string",
			"initialValue": "Enemies",
			"comment": "",
			"isStatic": false,
			"isConstant": true,
			"sid": 430835665973979
		},
		{
			"eventType": "variable",
			"name": "PT_Upgrades",
			"type": "string",
			"initialValue": "Upgrades",
			"comment": "",
			"isStatic": false,
			"isConstant": true,
			"sid": 123819595005711
		},
		{
			"eventType": "variable",
			"name": "PT_Items",
			"type": "string",
			"initialValue": "Items",
			"comment": "",
			"isStatic": false,
			"isConstant": true,
			"sid": 502481881529950
		},
		{
			"eventType": "comment",
			"text": "Roles"
		},
		{
			"eventType": "variable",
			"name": "ROLE_DevLog",
			"type": "string",
			"initialValue": "DevLog",
			"comment": "",
			"isStatic": false,
			"isConstant": true,
			"sid": 993471557987743
		},
		{
			"eventType": "variable",
			"name": "ROLE_Experience",
			"type": "string",
			"initialValue": "Experience",
			"comment": "",
			"isStatic": false,
			"isConstant": true,
			"sid": 624490682212020
		},
		{
			"eventType": "variable",
			"name": "ROLE_Health",
			"type": "string",
			"initialValue": "Health",
			"comment": "",
			"isStatic": false,
			"isConstant": true,
			"sid": 462448438943379
		},
		{
			"eventType": "comment",
			"text": "Sound effects"
		},
		{
			"eventType": "variable",
			"name": "SFX_DropPickup",
			"type": "string",
			"initialValue": "DropPickup",
			"comment": "",
			"isStatic": false,
			"isConstant": true,
			"sid": 907093821045628
		},
		{
			"eventType": "variable",
			"name": "SFX_EnemyDamaged",
			"type": "string",
			"initialValue": "EnemyDamaged",
			"comment": "",
			"isStatic": false,
			"isConstant": true,
			"sid": 306380490225541
		},
		{
			"eventType": "variable",
			"name": "SFX_LevelUp",
			"type": "string",
			"initialValue": "LevelUp",
			"comment": "",
			"isStatic": false,
			"isConstant": true,
			"sid": 114056398490478
		},
		{
			"eventType": "variable",
			"name": "SFX_PlayerDamaged",
			"type": "string",
			"initialValue": "PlayerDamaged",
			"comment": "",
			"isStatic": false,
			"isConstant": true,
			"sid": 547606269696265
		},
		{
			"eventType": "variable",
			"name": "SFX_PlayerDead",
			"type": "string",
			"initialValue": "PlayerDead",
			"comment": "",
			"isStatic": false,
			"isConstant": true,
			"sid": 894823877716605
		},
		{
			"eventType": "variable",
			"name": "SFX_UpgradeApplied",
			"type": "string",
			"initialValue": "UpgradeApplied",
			"comment": "",
			"isStatic": false,
			"isConstant": true,
			"sid": 332482984239385
		},
		{
			"eventType": "variable",
			"name": "SFX_UpgradeSelected",
			"type": "string",
			"initialValue": "UpgradeSelected",
			"comment": "",
			"isStatic": false,
			"isConstant": true,
			"sid": 315200725405928
		},
		{
			"eventType": "comment",
			"text": "Timers"
		},
		{
			"eventType": "variable",
			"name": "TIMER_FlashOn",
			"type": "string",
			"initialValue": "FlashOn",
			"comment": "",
			"isStatic": false,
			"isConstant": true,
			"sid": 773465413025330
		},
		{
			"eventType": "variable",
			"name": "TIMER_FlashOff",
			"type": "string",
			"initialValue": "FlashOff",
			"comment": "",
			"isStatic": false,
			"isConstant": true,
			"sid": 631897334080321
		},
		{
			"eventType": "variable",
			"name": "TIMER_Wave",
			"type": "string",
			"initialValue": "Wave",
			"comment": "",
			"isStatic": false,
			"isConstant": true,
			"sid": 313021126891210
		},
		{
			"eventType": "variable",
			"name": "TIMER_WaveCycle",
			"type": "string",
			"initialValue": "WaveCycle",
			"comment": "",
			"isStatic": false,
			"isConstant": true,
			"sid": 520331853285767
		},
		{
			"eventType": "variable",
			"name": "TIMER_Weapon_Attack_",
			"type": "string",
			"initialValue": "Weapon_Attack_",
			"comment": "",
			"isStatic": false,
			"isConstant": true,
			"sid": 706765231442737
		},
		{
			"eventType": "comment",
			"text": "Tweens"
		},
		{
			"eventType": "variable",
			"name": "TWEEN_LevelUp_FadeIn",
			"type": "string",
			"initialValue": "FadeIn",
			"comment": "",
			"isStatic": false,
			"isConstant": true,
			"sid": 916865266777374
		},
		{
			"eventType": "variable",
			"name": "TWEEN_LevelUp_FadeOut",
			"type": "string",
			"initialValue": "FadeOut",
			"comment": "",
			"isStatic": false,
			"isConstant": true,
			"sid": 934132276170255
		},
		{
			"eventType": "variable",
			"name": "TWEEN_Projectile_Opacity_Lifetime",
			"type": "string",
			"initialValue": "Opacity_Lifetime",
			"comment": "",
			"isStatic": false,
			"isConstant": true,
			"sid": 268804068231088
		},
		{
			"eventType": "variable",
			"name": "TWEEN_UI_TextSF_DamageNumber_Destroy",
			"type": "string",
			"initialValue": "Destroy",
			"comment": "",
			"isStatic": false,
			"isConstant": true,
			"sid": 998609837446816
		},
		{
			"eventType": "variable",
			"name": "TWEEN_UI_TextSF_DamageNumber_Scale",
			"type": "string",
			"initialValue": "Scale",
			"comment": "",
			"isStatic": false,
			"isConstant": true,
			"sid": 165491564316690
		},
		{
			"eventType": "group",
			"disabled": false,
			"title": "Unused",
			"description": "",
			"isActiveOnStart": false,
			"children": [
				{
					"eventType": "comment",
					"text": "Animations"
				},
				{
					"eventType": "variable",
					"name": "ANIM_Animation1",
					"type": "string",
					"initialValue": "Animation1",
					"comment": "",
					"isStatic": false,
					"isConstant": true,
					"sid": 327059335358554
				},
				{
					"eventType": "comment",
					"text": "Directions"
				},
				{
					"eventType": "variable",
					"name": "DIR_Up",
					"type": "string",
					"initialValue": "Up",
					"comment": "",
					"isStatic": false,
					"isConstant": true,
					"sid": 207033402076051
				},
				{
					"eventType": "variable",
					"name": "DIR_Down",
					"type": "string",
					"initialValue": "Down",
					"comment": "",
					"isStatic": false,
					"isConstant": true,
					"sid": 256893548866550
				},
				{
					"eventType": "variable",
					"name": "DIR_Left",
					"type": "string",
					"initialValue": "Left",
					"comment": "",
					"isStatic": false,
					"isConstant": true,
					"sid": 382424339529071
				},
				{
					"eventType": "variable",
					"name": "DIR_Right",
					"type": "string",
					"initialValue": "Right",
					"comment": "",
					"isStatic": false,
					"isConstant": true,
					"sid": 335289471851220
				},
				{
					"eventType": "comment",
					"text": "Effects"
				},
				{
					"eventType": "variable",
					"name": "EFFECTS_Effect1",
					"type": "string",
					"initialValue": "Effect1",
					"comment": "",
					"isStatic": false,
					"isConstant": true,
					"sid": 165756906028584
				},
				{
					"eventType": "comment",
					"text": "Object types"
				},
				{
					"eventType": "variable",
					"name": "OT_ObjectType1",
					"type": "string",
					"initialValue": "ObjectType1",
					"comment": "",
					"isStatic": false,
					"isConstant": true,
					"sid": 663173100308429
				},
				{
					"eventType": "comment",
					"text": "Signals"
				},
				{
					"eventType": "variable",
					"name": "SIGNAL_Signal1",
					"type": "string",
					"initialValue": "Signal1",
					"comment": "",
					"isStatic": false,
					"isConstant": true,
					"sid": 342181889607606
				},
				{
					"eventType": "comment",
					"text": "Templates"
				},
				{
					"eventType": "variable",
					"name": "TEMPLATE_Template1",
					"type": "string",
					"initialValue": "Template1",
					"comment": "",
					"isStatic": false,
					"isConstant": true,
					"sid": 891747630377562
				}
			],
			"sid": 667959762832484
		}
	],
	"sid": 781427496209080
}