{
	"name": "@ Templates",
	"layers": [
		{
			"name": "Layer 0",
			"overriden": 0,
			"subLayers": [],
			"instances": [
				{
					"type": "PlayerHurtbox",
					"properties": {
						"initially-visible": false,
						"initial-animation": "Animation 1",
						"initial-frame": 0,
						"enable-collisions": true,
						"live-preview": false
					},
					"uid": 48,
					"sid": 208279347654933,
					"tags": "",
					"instanceVariables": {},
					"behaviors": {},
					"sceneGraphData": {
						"parent-uid": 3,
						"uid": 48,
						"flags": {
							"x": true,
							"y": true,
							"z": false,
							"w": true,
							"h": true,
							"a": true,
							"o": false,
							"v": false,
							"d": true,
							"sm": "normal"
						},
						"preview": {
							"transformX": 0,
							"transformY": 0,
							"transformZElevation": 0,
							"transformW": 0,
							"transformH": 0,
							"transformA": 0,
							"transformSX": 0,
							"transformSY": 0,
							"transformO": 0,
							"previewSceneGraph": false
						}
					},
					"instanceFolderItem": {
						"sid": 208279347654933,
						"expanded": true
					},
					"showing": true,
					"locked": false,
					"world": {
						"x": 16,
						"y": 34,
						"width": 12,
						"height": 12,
						"originX": 0.5,
						"originY": 0.5,
						"color": [
							1,
							1,
							1,
							1
						],
						"angle": 0,
						"zElevation": 0
					}
				},
				{
					"type": "Weapon",
					"properties": {
						"initially-visible": true,
						"initial-animation": "Axe",
						"initial-frame": 0,
						"enable-collisions": true,
						"live-preview": false
					},
					"uid": 10,
					"sid": 700222683177902,
					"tags": "",
					"instanceVariables": {
						"damage": 0,
						"isMovementBlocker": 0,
						"isDestroyed": 0,
						"piercedUIDs_SSV": ""
					},
					"behaviors": {
						"Bullet": {
							"properties": {
								"speed": 0,
								"acceleration": 0,
								"gravity": 0,
								"bounce-off-solids": false,
								"set-angle": false,
								"step": false,
								"enabled": true
							}
						},
						"Tween": {
							"properties": {
								"enabled": true
							}
						},
						"Orbit": {
							"properties": {
								"speed": 0,
								"acceleration": 0,
								"primary-axis": 0,
								"secondary-axis": 0,
								"offset-angle": 0,
								"match-rotation": true,
								"enabled": false,
								"live-preview": false
							}
						},
						"Rotate": {
							"properties": {
								"speed": 0,
								"acceleration": 0,
								"enabled": true,
								"live-preview": false
							}
						}
					},
					"instanceFolderItem": {
						"sid": 700222683177902,
						"expanded": true
					},
					"showing": true,
					"locked": false,
					"world": {
						"x": 8,
						"y": 116,
						"width": 16,
						"height": 16,
						"originX": 0.5,
						"originY": 0.5,
						"color": [
							1,
							1,
							1,
							1
						],
						"angle": 0,
						"zElevation": 0
					}
				},
				{
					"type": "Enemy",
					"properties": {
						"initially-visible": true,
						"initial-animation": "Default",
						"initial-frame": 0,
						"enable-collisions": true,
						"live-preview": false
					},
					"uid": 4,
					"sid": 667473189291264,
					"tags": "",
					"instanceVariables": {
						"damageTakenRecently": 0,
						"health": 0,
						"damage": 0,
						"experience": 0,
						"healing": 0,
						"isDead": 0,
						"isContainer": 0,
						"isMovementBlocked": 0,
						"movementSpeed": 0,
						"movementAngle": -1
					},
					"behaviors": {
						"Physics": {
							"properties": {
								"immovable": true,
								"collision-mask": "circle",
								"prevent-rotation": true,
								"density": 1,
								"friction": 0,
								"elasticity": 0,
								"linear-damping": 100,
								"angular-damping": 1,
								"bullet": false,
								"enabled": true
							}
						},
						"Tween": {
							"properties": {
								"enabled": true
							}
						},
						"Timer": {
							"properties": {}
						}
					},
					"sceneGraphData": {
						"parent-uid": null,
						"uid": 4,
						"children": [
							{
								"uid": 37,
								"flags": {
									"x": false,
									"y": false,
									"z": false,
									"w": false,
									"h": false,
									"a": false,
									"o": false,
									"v": false,
									"d": true,
									"sm": "normal"
								}
							}
						],
						"flags": {
							"x": true,
							"y": true,
							"z": true,
							"w": true,
							"h": true,
							"a": true,
							"o": false,
							"v": false,
							"d": true,
							"sm": "normal"
						},
						"preview": {
							"transformX": 0,
							"transformY": 0,
							"transformZElevation": 0,
							"transformW": 0,
							"transformH": 0,
							"transformA": 0,
							"transformSX": 0,
							"transformSY": 0,
							"transformO": 0,
							"previewSceneGraph": false
						}
					},
					"instanceFolderItem": {
						"sid": 667473189291264,
						"expanded": true
					},
					"showing": true,
					"locked": false,
					"world": {
						"x": 137,
						"y": 44,
						"width": 27,
						"height": 27,
						"originX": 0.5,
						"originY": 0.5,
						"color": [
							1,
							1,
							1,
							1
						],
						"angle": 0,
						"zElevation": 0
					}
				},
				{
					"type": "Drop",
					"properties": {
						"initially-visible": true,
						"initial-animation": "Default",
						"initial-frame": 0,
						"enable-collisions": true,
						"live-preview": false
					},
					"uid": 11,
					"sid": 691388145451267,
					"tags": "",
					"instanceVariables": {
						"experience": 0,
						"healing": 0,
						"isCollected": 0
					},
					"behaviors": {
						"Bullet": {
							"properties": {
								"speed": 10,
								"acceleration": 100,
								"gravity": 0,
								"bounce-off-solids": false,
								"set-angle": false,
								"step": false,
								"enabled": false
							}
						}
					},
					"instanceFolderItem": {
						"sid": 691388145451267,
						"expanded": true
					},
					"showing": true,
					"locked": false,
					"world": {
						"x": 57,
						"y": 102,
						"width": 12,
						"height": 12,
						"originX": 0.5,
						"originY": 0.5,
						"color": [
							1,
							1,
							1,
							1
						],
						"angle": 0,
						"zElevation": 0
					}
				},
				{
					"type": "Player",
					"properties": {
						"initially-visible": true,
						"initial-animation": "Walking",
						"initial-frame": 0,
						"enable-collisions": true,
						"live-preview": false
					},
					"uid": 3,
					"sid": 275528799847544,
					"tags": "",
					"instanceVariables": {
						"level": 1,
						"experience": 0,
						"isDead": 0,
						"isHurt": 0,
						"lastMovingAngle": 0,
						"IN_Vector_X": 0,
						"IN_Vector_Y": 0,
						"IN_Movement_Active": 0,
						"IN_Movement_Angle": 0
					},
					"behaviors": {
						"8Direction": {
							"properties": {
								"max-speed": 0,
								"acceleration": 0,
								"deceleration": 0,
								"directions": "dir-8",
								"set-angle": "no",
								"allow-sliding": true,
								"default-controls": false,
								"enabled": true
							}
						},
						"ScrollTo": {
							"properties": {
								"enabled": true
							}
						},
						"Tween": {
							"properties": {
								"enabled": true
							}
						},
						"Physics": {
							"properties": {
								"immovable": true,
								"collision-mask": "use-collision-polygon",
								"prevent-rotation": false,
								"density": 1,
								"friction": 0,
								"elasticity": 0,
								"linear-damping": 0,
								"angular-damping": 0.01,
								"bullet": false,
								"enabled": true
							}
						},
						"Timer": {
							"properties": {}
						}
					},
					"sceneGraphData": {
						"parent-uid": null,
						"uid": 3,
						"children": [
							{
								"uid": 48,
								"flags": {
									"x": true,
									"y": true,
									"z": false,
									"w": true,
									"h": true,
									"a": true,
									"o": false,
									"v": false,
									"d": true,
									"sm": "normal"
								}
							},
							{
								"uid": 25,
								"flags": {
									"x": true,
									"y": true,
									"z": false,
									"w": false,
									"h": false,
									"a": false,
									"o": false,
									"v": false,
									"d": true,
									"sm": "normal"
								}
							}
						],
						"flags": {
							"x": true,
							"y": true,
							"z": true,
							"w": true,
							"h": true,
							"a": true,
							"o": false,
							"v": false,
							"d": true,
							"sm": "normal"
						},
						"preview": {
							"transformX": 0,
							"transformY": 0,
							"transformZElevation": 0,
							"transformW": 0,
							"transformH": 0,
							"transformA": 0,
							"transformSX": 0,
							"transformSY": 0,
							"transformO": 0,
							"previewSceneGraph": false
						}
					},
					"instanceFolderItem": {
						"sid": 275528799847544,
						"expanded": true
					},
					"showing": true,
					"locked": false,
					"world": {
						"x": 16,
						"y": 33,
						"width": 16,
						"height": 16,
						"originX": 0.5,
						"originY": 0.5,
						"color": [
							1,
							1,
							1,
							1
						],
						"angle": 0,
						"zElevation": 0
					}
				},
				{
					"type": "Map",
					"properties": {
						"initially-visible": true,
						"tile-width": 8,
						"tile-height": 8,
						"tile-x-offset": 0,
						"tile-y-offset": 0,
						"tile-x-spacing": 0,
						"tile-y-spacing": 0,
						"tile-x-drawing-offset": 0,
						"tile-y-drawing-offset": 0,
						"drawing-mode": "top-to-right"
					},
					"uid": 9,
					"sid": 771978116621594,
					"tags": "",
					"instanceVariables": {},
					"behaviors": {
						"Solid": {
							"properties": {
								"enabled": false,
								"tags": ""
							}
						},
						"Physics": {
							"properties": {
								"immovable": true,
								"collision-mask": "use-collision-polygon",
								"prevent-rotation": false,
								"density": 1,
								"friction": 0,
								"elasticity": 0,
								"linear-damping": 0,
								"angular-damping": 0.01,
								"bullet": false,
								"enabled": false
							}
						}
					},
					"ownData": {
						"tilemapData": {
							"width": 14,
							"height": 1,
							"max-width": 51,
							"max-height": 23,
							"data": "1,5x45hd,44vd,16x0,2,5x0,45,16x0,3,5x0,45,16x0,4,5x0,45,16x0,5,5x0,45,16x0,6,5x0,45,16x0,7,5x45hd,44hv,16x0,8,22x0,9,22x0,10,22x0,11,22x0,12,22x0,13,22x0,14,873x0"
						},
						"tile-width": 8,
						"tile-height": 8,
						"tile-x-offset": 0,
						"tile-y-offset": 0,
						"tile-x-spacing": 0,
						"tile-y-spacing": 0
					},
					"instanceFolderItem": {
						"sid": 771978116621594,
						"expanded": true
					},
					"showing": true,
					"locked": false,
					"world": {
						"x": 78,
						"y": 8,
						"width": 112,
						"height": 8,
						"originX": 0,
						"originY": 0,
						"color": [
							1,
							1,
							1,
							0.6
						],
						"zElevation": 0
					}
				},
				{
					"type": "Ground",
					"properties": {
						"initially-visible": true,
						"origin": "top-left",
						"wrap-horizontal": "repeat",
						"wrap-vertical": "repeat",
						"image-offset-x": 0,
						"image-offset-y": 0,
						"image-scale-x": 1,
						"image-scale-y": 1,
						"image-angle": 0,
						"enable-tile-randomization": false,
						"x-random": 1,
						"y-random": 1,
						"angle-random": 0,
						"blend-margin-x": 0,
						"blend-margin-y": 0
					},
					"uid": 2,
					"sid": 254569359469305,
					"tags": "",
					"instanceVariables": {},
					"behaviors": {},
					"instanceFolderItem": {
						"sid": 254569359469305,
						"expanded": true
					},
					"showing": true,
					"locked": false,
					"world": {
						"x": 62,
						"y": 26,
						"width": 42,
						"height": 43,
						"originX": 0,
						"originY": 0,
						"color": [
							0.7294117647058823,
							0.3803921568627451,
							0.33725490196078434,
							0.1
						],
						"angle": 0,
						"zElevation": 0
					}
				},
				{
					"type": "Wall",
					"properties": {
						"initially-visible": true,
						"origin": "center",
						"wrap-horizontal": "repeat",
						"wrap-vertical": "repeat",
						"image-offset-x": 0,
						"image-offset-y": 0,
						"image-scale-x": 1,
						"image-scale-y": 1,
						"image-angle": 0,
						"enable-tile-randomization": false,
						"x-random": 0,
						"y-random": 0,
						"angle-random": 0,
						"blend-margin-x": 0,
						"blend-margin-y": 0
					},
					"uid": 12,
					"sid": 957709863655658,
					"tags": "",
					"instanceVariables": {},
					"behaviors": {
						"Solid": {
							"properties": {
								"enabled": true,
								"tags": ""
							}
						}
					},
					"instanceFolderItem": {
						"sid": 957709863655658,
						"expanded": true
					},
					"showing": true,
					"locked": false,
					"world": {
						"x": 193,
						"y": 42,
						"width": 32,
						"height": 32,
						"originX": 0.5,
						"originY": 0.5,
						"color": [
							1,
							1,
							1,
							1
						],
						"angle": 0,
						"zElevation": 0
					}
				},
				{
					"type": "Item",
					"properties": {
						"initially-visible": true,
						"initial-animation": "Default",
						"initial-frame": 0,
						"enable-collisions": true,
						"live-preview": false
					},
					"uid": 14,
					"sid": 896172996303602,
					"tags": "",
					"instanceVariables": {
						"modifier": "",
						"isPickedUp": 0
					},
					"behaviors": {
						"Tween": {
							"properties": {
								"enabled": true
							}
						}
					},
					"instanceFolderItem": {
						"sid": 896172996303602,
						"expanded": true
					},
					"showing": true,
					"locked": false,
					"world": {
						"x": 30,
						"y": 151,
						"width": 18,
						"height": 18,
						"originX": 0.5,
						"originY": 0.5,
						"color": [
							1,
							1,
							1,
							1
						],
						"angle": 0,
						"zElevation": 0
					}
				},
				{
					"type": "UI_TextSF_Damage",
					"properties": {
						"text": "1234567",
						"enable-bbcode": false,
						"character-width": 5,
						"character-height": 7,
						"character-set": "ABCDEFGHIJKLMNOPQRSTUVWXYZ1234567890.,;:?!-_~#\"'()[]|°%+*\\/=<> ",
						"spacing-data": "[[4,\"ABCDEFGHJKLMNOPQRSTUVWXYZ1234567890?-_~#°%+*\\/=<>\"],[3,\",;()[] \"],[2,\"|I.:!'\"]]",
						"scale": 0.75,
						"character-spacing": 0,
						"line-height": 1,
						"horizontal-alignment": "center",
						"vertical-alignment": "center",
						"wrapping": "word",
						"initially-visible": false,
						"origin": "center",
						"read-aloud": false
					},
					"uid": 37,
					"sid": 843334077670080,
					"tags": "",
					"instanceVariables": {},
					"behaviors": {
						"Tween": {
							"properties": {
								"enabled": true
							}
						}
					},
					"sceneGraphData": {
						"parent-uid": 4,
						"uid": 37,
						"flags": {
							"x": false,
							"y": false,
							"z": false,
							"w": false,
							"h": false,
							"a": false,
							"o": false,
							"v": false,
							"d": true,
							"sm": "normal"
						},
						"preview": {
							"transformX": 0,
							"transformY": 0,
							"transformZElevation": 0,
							"transformW": 0,
							"transformH": 0,
							"transformA": 0,
							"transformSX": 0,
							"transformSY": 0,
							"transformO": 0,
							"previewSceneGraph": false
						}
					},
					"instanceFolderItem": {
						"sid": 843334077670080,
						"expanded": true
					},
					"showing": true,
					"locked": false,
					"world": {
						"x": 137,
						"y": 44,
						"width": 32,
						"height": 8,
						"originX": 0.5,
						"originY": 0.5,
						"color": [
							1,
							1,
							1,
							1
						],
						"angle": 0,
						"zElevation": 0
					}
				},
				{
					"type": "Arrow",
					"properties": {
						"initially-visible": true,
						"initial-animation": "Animation 1",
						"initial-frame": 0,
						"enable-collisions": true,
						"live-preview": false
					},
					"uid": 35,
					"sid": 941515962273430,
					"tags": "",
					"instanceVariables": {
						"itemX": 0,
						"itemY": 0
					},
					"behaviors": {},
					"instanceFolderItem": {
						"sid": 941515962273430,
						"expanded": true
					},
					"showing": true,
					"locked": false,
					"world": {
						"x": 57,
						"y": 95,
						"width": 16,
						"height": 16,
						"originX": -4,
						"originY": 0.5,
						"color": [
							1,
							1,
							1,
							1
						],
						"angle": 0,
						"zElevation": 0,
						"blendMode": "additive"
					}
				},
				{
					"type": "UI_TextSF_GameOver",
					"properties": {
						"text": "GAME OVER\n\n[scale=0.2]Click or tap & hold here to restart",
						"enable-bbcode": true,
						"character-width": 30,
						"character-height": 30,
						"character-set": " !\"#$%&'()*+,-./0123456789:;<=>?@ABCDEFGHIJKLMNOPQRSTUVWXYZ[\\]^_`abcdefghijklmnopqrstuvwxyz{|}~",
						"spacing-data": "[[12,\" \"],[24,\"!\\\"#$%&'()*+,-./0123456789:;<=>?@ABCDEFGHIJKLMNOPQRSTUVWXYZ[\\]^_`abcdefghijklmnopqrstuvwxyz{|}~\"]]",
						"scale": 0.6,
						"character-spacing": 0,
						"line-height": 0,
						"horizontal-alignment": "center",
						"vertical-alignment": "center",
						"wrapping": "word",
						"initially-visible": true,
						"origin": "center",
						"read-aloud": false
					},
					"uid": 53,
					"sid": 459953218896000,
					"tags": "",
					"instanceVariables": {},
					"behaviors": {},
					"sceneGraphData": {
						"parent-uid": null,
						"uid": 53,
						"flags": {
							"x": true,
							"y": true,
							"z": false,
							"w": false,
							"h": false,
							"a": false,
							"o": true,
							"v": true,
							"d": true,
							"sm": "normal"
						},
						"preview": {
							"transformX": 0,
							"transformY": 0,
							"transformZElevation": 0,
							"transformW": 0,
							"transformH": 0,
							"transformA": 0,
							"transformSX": 0,
							"transformSY": 0,
							"transformO": 0,
							"previewSceneGraph": false
						}
					},
					"instanceFolderItem": {
						"sid": 459953218896000,
						"expanded": true
					},
					"showing": true,
					"locked": false,
					"world": {
						"x": 187,
						"y": 145,
						"width": 236,
						"height": 48,
						"originX": 0.5,
						"originY": 0.5,
						"color": [
							1,
							1,
							1,
							1
						],
						"angle": 0,
						"zElevation": 0
					}
				},
				{
					"type": "UI_TextSF_Wave",
					"properties": {
						"text": "Wave 1",
						"enable-bbcode": true,
						"character-width": 30,
						"character-height": 30,
						"character-set": " !\"#$%&'()*+,-./0123456789:;<=>?@ABCDEFGHIJKLMNOPQRSTUVWXYZ[\\]^_`abcdefghijklmnopqrstuvwxyz{|}~🅰🅱©",
						"spacing-data": "[[12,\" \"],[24,\"!\\\"#$%&'()*+,-./0123456789:;<=>?@ABCDEFGHIJKLMNOPQRSTUVWXYZ[\\]^_`abcdefghijklmnopqrstuvwxyz{|}~\"]]",
						"scale": 0.2,
						"character-spacing": 0,
						"line-height": 0,
						"horizontal-alignment": "center",
						"vertical-alignment": "center",
						"wrapping": "word",
						"initially-visible": true,
						"origin": "top",
						"read-aloud": false
					},
					"uid": 55,
					"sid": 327675846567885,
					"tags": "",
					"instanceVariables": {},
					"behaviors": {
						"Tween": {
							"properties": {
								"enabled": true
							}
						}
					},
					"sceneGraphData": {
						"parent-uid": null,
						"uid": 55,
						"flags": {
							"x": true,
							"y": true,
							"z": false,
							"w": false,
							"h": false,
							"a": false,
							"o": true,
							"v": true,
							"d": true,
							"sm": "normal"
						},
						"preview": {
							"transformX": 0,
							"transformY": 0,
							"transformZElevation": 0,
							"transformW": 0,
							"transformH": 0,
							"transformA": 0,
							"transformSX": 0,
							"transformSY": 0,
							"transformO": 0,
							"previewSceneGraph": false
						}
					},
					"instanceFolderItem": {
						"sid": 327675846567885,
						"expanded": true
					},
					"showing": true,
					"locked": false,
					"world": {
						"x": 160,
						"y": 184,
						"width": 320,
						"height": 16,
						"originX": 0.5,
						"originY": 0,
						"color": [
							1,
							1,
							1,
							1
						],
						"angle": 0,
						"zElevation": 0
					}
				},
				{
					"type": "UI_Background_Health",
					"properties": {
						"initially-visible": true,
						"origin": "top",
						"wrap-horizontal": "repeat",
						"wrap-vertical": "repeat",
						"image-offset-x": 0,
						"image-offset-y": 0,
						"image-scale-x": 1,
						"image-scale-y": 1,
						"image-angle": 0,
						"enable-tile-randomization": false,
						"x-random": 1,
						"y-random": 1,
						"angle-random": 1,
						"blend-margin-x": 0.1,
						"blend-margin-y": 0.1
					},
					"uid": 25,
					"sid": 633184746318915,
					"tags": "",
					"instanceVariables": {},
					"behaviors": {},
					"sceneGraphData": {
						"parent-uid": 3,
						"uid": 25,
						"children": [
							{
								"uid": 50,
								"flags": {
									"x": true,
									"y": true,
									"z": false,
									"w": false,
									"h": false,
									"a": false,
									"o": false,
									"v": false,
									"d": true,
									"sm": "normal"
								}
							}
						],
						"flags": {
							"x": true,
							"y": true,
							"z": false,
							"w": false,
							"h": false,
							"a": false,
							"o": false,
							"v": false,
							"d": true,
							"sm": "normal"
						},
						"preview": {
							"transformX": 0,
							"transformY": 0,
							"transformZElevation": 0,
							"transformW": 0,
							"transformH": 0,
							"transformA": 0,
							"transformSX": 0,
							"transformSY": 0,
							"transformO": 0,
							"previewSceneGraph": false
						}
					},
					"instanceFolderItem": {
						"sid": 633184746318915,
						"expanded": true
					},
					"showing": true,
					"locked": false,
					"world": {
						"x": 16,
						"y": 43,
						"width": 16,
						"height": 1,
						"originX": 0.5,
						"originY": 0,
						"color": [
							1,
							1,
							1,
							1
						],
						"angle": 0,
						"zElevation": 0
					}
				},
				{
					"type": "UI_Bar_Health",
					"properties": {
						"initially-visible": true,
						"origin": "top-left",
						"wrap-horizontal": "repeat",
						"wrap-vertical": "repeat",
						"image-offset-x": 0,
						"image-offset-y": 0,
						"image-scale-x": 1,
						"image-scale-y": 1,
						"image-angle": 0,
						"enable-tile-randomization": false,
						"x-random": 1,
						"y-random": 1,
						"angle-random": 1,
						"blend-margin-x": 0.1,
						"blend-margin-y": 0.1
					},
					"uid": 50,
					"sid": 858825885389928,
					"tags": "",
					"instanceVariables": {
						"initWidth": 0
					},
					"behaviors": {},
					"sceneGraphData": {
						"parent-uid": 25,
						"uid": 50,
						"flags": {
							"x": true,
							"y": true,
							"z": false,
							"w": false,
							"h": false,
							"a": false,
							"o": false,
							"v": false,
							"d": true,
							"sm": "normal"
						},
						"preview": {
							"transformX": 0,
							"transformY": 0,
							"transformZElevation": 0,
							"transformW": 0,
							"transformH": 0,
							"transformA": 0,
							"transformSX": 0,
							"transformSY": 0,
							"transformO": 0,
							"previewSceneGraph": false
						}
					},
					"instanceFolderItem": {
						"sid": 858825885389928,
						"expanded": true
					},
					"showing": true,
					"locked": false,
					"world": {
						"x": 8,
						"y": 43,
						"width": 16,
						"height": 1,
						"originX": 0,
						"originY": 0,
						"color": [
							1,
							1,
							1,
							1
						],
						"angle": 0,
						"zElevation": 0
					}
				}
			],
			"sid": 435828509073843,
			"effectTypes": [],
			"isInitiallyVisible": true,
			"isInitiallyInteractive": true,
			"isHTMLElementsLayer": false,
			"color": [
				1,
				1,
				1,
				1
			],
			"backgroundColor": [
				0.3686274509803922,
				0.3686274509803922,
				0.3686274509803922,
				1
			],
			"isTransparent": false,
			"parallaxX": 1,
			"parallaxY": 1,
			"scaleRate": 1,
			"forceOwnTexture": false,
			"renderingMode": "3d",
			"drawOrder": "z-order",
			"useRenderCells": false,
			"blendMode": "normal",
			"zElevation": 0,
			"global": false
		}
	],
	"scene-graphs-folder-root": {
		"items": [],
		"subfolders": []
	},
	"sid": 660448592118930,
	"nonworld-instances": [],
	"effectTypes": [],
	"width": 600,
	"height": 600,
	"unboundedScrolling": false,
	"vpX": 0.5,
	"vpY": 0.5,
	"projection": "perspective",
	"eventSheet": null
}